meshiphi/__init__.py
meshiphi/cli.py
meshiphi/utils.py
meshiphi/config_validation/__init__.py
meshiphi/config_validation/config_validator.py
meshiphi/config_validation/mesh_schema.py
meshiphi/config_validation/route_schema.py
meshiphi/config_validation/vessel_schema.py
meshiphi/config_validation/waypoints_schema.py
meshiphi/dataloaders/__init__.py
meshiphi/dataloaders/dataloader_interface.py
meshiphi/dataloaders/factory.py
meshiphi/dataloaders/lut/__init__.py
meshiphi/dataloaders/lut/abstract_lut.py
meshiphi/dataloaders/lut/density.py
meshiphi/dataloaders/lut/lut_csv.py
meshiphi/dataloaders/lut/lut_geojson.py
meshiphi/dataloaders/lut/lut_shapefile.py
meshiphi/dataloaders/lut/scotland_ncmpa.py
meshiphi/dataloaders/lut/thickness.py
meshiphi/dataloaders/scalar/__init__.py
meshiphi/dataloaders/scalar/abstract_scalar.py
meshiphi/dataloaders/scalar/amsr.py
meshiphi/dataloaders/scalar/baltic_sea_ice.py
meshiphi/dataloaders/scalar/bsose_depth.py
meshiphi/dataloaders/scalar/bsose_sea_ice.py
meshiphi/dataloaders/scalar/ecmwf_sig_wave_height.py
meshiphi/dataloaders/scalar/era5_max_wave_height.py
meshiphi/dataloaders/scalar/era5_mean_wave_direction.py
meshiphi/dataloaders/scalar/era5_sig_wave_height.py
meshiphi/dataloaders/scalar/era5_wave_period.py
meshiphi/dataloaders/scalar/era5_wind_dir.py
meshiphi/dataloaders/scalar/era5_wind_mag.py
meshiphi/dataloaders/scalar/gebco.py
meshiphi/dataloaders/scalar/icenet.py
meshiphi/dataloaders/scalar/modis.py
meshiphi/dataloaders/scalar/scalar_csv.py
meshiphi/dataloaders/scalar/scalar_grf.py
meshiphi/dataloaders/scalar/shape.py
meshiphi/dataloaders/scalar/visual_iced.py
meshiphi/dataloaders/vector/__init__.py
meshiphi/dataloaders/vector/abstract_vector.py
meshiphi/dataloaders/vector/baltic_current.py
meshiphi/dataloaders/vector/duacs_current.py
meshiphi/dataloaders/vector/era5_wave_direction_vector.py
meshiphi/dataloaders/vector/era5_wind.py
meshiphi/dataloaders/vector/north_sea_current.py
meshiphi/dataloaders/vector/oras5_current.py
meshiphi-2.1.15.dist-info/LICENSE
meshiphi-2.1.15.dist-info/METADATA
meshiphi-2.1.15.dist-info/WHEEL
meshiphi-2.1.15.dist-info/entry_points.txt
meshiphi-2.1.15.dist-info/top_level.txt
meshiphi-2.1.15.dist-info/RECORD
